eye_tools/__init__.py
eye_tools/__main__.py
eye_tools/analysis_tools.py
eye_tools/interfaces.py
eye_tools/lattice_builder.py
compound_eye_tools-2021.1.3.4.dist-info/LICENSE
compound_eye_tools-2021.1.3.4.dist-info/METADATA
compound_eye_tools-2021.1.3.4.dist-info/WHEEL
compound_eye_tools-2021.1.3.4.dist-info/top_level.txt
compound_eye_tools-2021.1.3.4.dist-info/RECORD
