Metadata-Version: 2.1
Name: compound-eye-tools
Version: 2021.1.3.4
Summary: Image analysis toos for extracting optical parameters of compound eyes.
Home-page: https://github.com/jpcurrea/eye_tools
Author: John Paul Currea
Author-email: johnpaulcurrea@gmail.com
License: UNKNOWN
Project-URL: Documentation, https://jpcurrea.github.io/eye_tools/,
Project-URL: Source, https://github.com/jpcurrea/eye_tools
Platform: UNKNOWN
Classifier: Programming Language :: Python :: 3
Classifier: License :: OSI Approved :: MIT License
Classifier: Operating System :: OS Independent
Requires-Python: >=3.6
License-File: LICENSE
